workbook/__init__.py
gtagora_workbook_py-0.0.1.dist-info/LICENSE
gtagora_workbook_py-0.0.1.dist-info/METADATA
gtagora_workbook_py-0.0.1.dist-info/WHEEL
gtagora_workbook_py-0.0.1.dist-info/top_level.txt
gtagora_workbook_py-0.0.1.dist-info/RECORD
