Metadata-Version: 2.1
Name: gtagora-workbook-py
Version: 0.0.1
Summary: Agora workbook utilities
Author-email: Martin Buehrer <martin.buehrer@gyrotools.com>
Maintainer-email: Martin Buehrer <martin.buehrer@gyrotools.com>
License: MIT License
Project-URL: Homepage, https://github.com/GyroTools/gtagora-workbook-py
Project-URL: Source, https://github.com/GyroTools/gtagora-workbook-py
Keywords: gyrotools,agora,workbook
Requires-Python: >=3.7
License-File: LICENSE
Provides-Extra: dev
Provides-Extra: test
Requires-Dist: pytest ; extra == 'test'
